{"status": "OK", "result": [{"id": 176420937, "contestId": 1746, "creationTimeSeconds": 1665893424, "relativeTimeSeconds": 2147483647, "problem": {"contestId": 1746, "index": "E1", "name": "Joking (Easy Version)", "type": "PROGRAMMING", "points": 2000.0, "rating": 2500, "tags": ["binary search", "constructive algorithms", "interactive", "ternary search"]}, "author": {"contestId": 1746, "members": [{"handle": "StaneLegend"}], "participantType": "PRACTICE", "ghost": false, "startTimeSeconds": 1665844500}, "programmingLanguage": "GNU C++20 (64)", "verdict": "OK", "testset": "TESTS", "passedTestCount": 54, "timeConsumedMillis": 62, "memoryConsumedBytes": 2150400}, {"id": 176417087, "contestId": 1746, "creationTimeSeconds": 1665889608, "relativeTimeSeconds": 2147483647, "problem": {"contestId": 1746, "index": "F", "name": "Kazaee", "type": "PROGRAMMING", "points": 2500.0, "rating": 2800, "tags": ["data structures", "hashing", "probabilities"]}, "author": {"contestId": 1746, "members": [{"handle": "StaneLegend"}], "participantType": "PRACTICE", "ghost": false, "startTimeSeconds": 1665844500}, "programmingLanguage": "GNU C++20 (64)", "verdict": "OK", "testset": "TESTS", "passedTestCount": 104, "timeConsumedMillis": 1809, "memoryConsumedBytes": 28672000}, {"id": 176342180, "contestId": 1746, "creationTimeSeconds": 1665847260, "relativeTimeSeconds": 2760, "problem": {"contestId": 1746, "index": "D", "name": "Paths on the Tree", "type": "PROGRAMMING", "points": 1500.0, "rating": 1900, "tags": ["dfs and similar", "dp", "greedy", "sortings", "trees"]}, "author": {"contestId": 1746, "members": [{"handle": "StaneLegend"}], "participantType": "CONTESTANT", "ghost": false, "room": 361, "startTimeSeconds": 1665844500}, "programmingLanguage": "GNU C++20 (64)", "verdict": "OK", "testset": "TESTS", "passedTestCount": 81, "timeConsumedMillis": 498, "memoryConsumedBytes": 59289600}, {"id": 176336227, "contestId": 1746, "creationTimeSeconds": 1665846616, "relativeTimeSeconds": 2116, "problem": {"contestId": 1746, "index": "D", "name": "Paths on the Tree", "type": "PROGRAMMING", "points": 1500.0, "rating": 1900, "tags": ["dfs and similar", "dp", "greedy", "sortings", "trees"]}, "author": {"contestId": 1746, "members": [{"handle": "StaneLegend"}], "participantType": "CONTESTANT", "ghost": false, "room": 361, "startTimeSeconds": 1665844500}, "programmingLanguage": "GNU C++20 (64)", "verdict": "TIME_LIMIT_EXCEEDED", "testset": "PRETESTS", "passedTestCount": 3, "timeConsumedMillis": 3000, "memoryConsumedBytes": 158208000}, {"id": 176326076, "contestId": 1746, "creationTimeSeconds": 1665845680, "relativeTimeSeconds": 1180, "problem": {"contestId": 1746, "index": "C", "name": "Permutation Operations", "type": "PROGRAMMING", "points": 1000.0, "rating": 1300, "tags": ["constructive algorithms", "greedy", "implementation", "math"]}, "author": {"contestId": 1746, "members": [{"handle": "StaneLegend"}], "participantType": "CONTESTANT", "ghost": false, "room": 361, "startTimeSeconds": 1665844500}, "programmingLanguage": "GNU C++20 (64)", "verdict": "OK", "testset": "TESTS", "passedTestCount": 60, "timeConsumedMillis": 234, "memoryConsumedBytes": 2457600}, {"id": 176322487, "contestId": 1746, "creationTimeSeconds": 1665845407, "relativeTimeSeconds": 907, "problem": {"contestId": 1746, "index": "B", "name": "Rebellion", "type": "PROGRAMMING", "points": 1000.0, "rating": 800, "tags": ["constructive algorithms", "greedy", "two pointers"]}, "author": {"contestId": 1746, "members": [{"handle": "StaneLegend"}], "participantType": "CONTESTANT", "ghost": false, "room": 361, "startTimeSeconds": 1665844500}, "programmingLanguage": "GNU C++20 (64)", "verdict": "OK", "testset": "TESTS", "passedTestCount": 20, "timeConsumedMillis": 171, "memoryConsumedBytes": 1228800}, {"id": 176310868, "contestId": 1746, "creationTimeSeconds": 1665844698, "relativeTimeSeconds": 198, "problem": {"contestId": 1746, "index": "A", "name": "Maxmina", "type": "PROGRAMMING", "points": 500.0, "rating": 800, "tags": ["constructive algorithms", "greedy"]}, "author": {"contestId": 1746, "members": [{"handle": "StaneLegend"}], "participantType": "CONTESTANT", "ghost": false, "room": 361, "startTimeSeconds": 1665844500}, "programmingLanguage": "GNU C++20 (64)", "verdict": "OK", "testset": "TESTS", "passedTestCount": 11, "timeConsumedMillis": 46, "memoryConsumedBytes": 0}, {"id": 175066653, "contestId": 1737, "creationTimeSeconds": 1665199061, "relativeTimeSeconds": 2147483647, "problem": {"contestId": 1737, "index": "C", "name": "Ela and Crickets", "type": "PROGRAMMING", "points": 1500.0, "rating": 1500, "tags": ["constructive algorithms", "games", "implementation", "math"]}, "author": {"contestId": 1737, "members": [{"handle": "StaneLegend"}], "participantType": "PRACTICE", "ghost": false, "startTimeSeconds": 1665153300}, "programmingLanguage": "GNU C++20 (64)", "verdict": "OK", "testset": "TESTS", "passedTestCount": 23, "timeConsumedMillis": 139, "memoryConsumedBytes": 0}, {"id": 175066523, "contestId": 1737, "creationTimeSeconds": 1665198898, "relativeTimeSeconds": 2147483647, "problem": {"contestId": 1737, "index": "C", "name": "Ela and Crickets", "type": "PROGRAMMING", "points": 1500.0, "rating": 1500, "tags": ["constructive algorithms", "games", "implementation", "math"]}, "author": {"contestId": 1737, "members": [{"handle": "StaneLegend"}], "participantType": "PRACTICE", "ghost": false, "startTimeSeconds": 1665153300}, "programmingLanguage": "GNU C++20 (64)", "verdict": "WRONG_ANSWER", "testset": "TESTS", "passedTestCount": 2, "timeConsumedMillis": 30, "memoryConsumedBytes": 0}, {"id": 175066457, "contestId": 1737, "creationTimeSeconds": 1665198801, "relativeTimeSeconds": 2147483647, "problem": {"contestId": 1737, "index": "C", "name": "Ela and Crickets", "type": "PROGRAMMING", "points": 1500.0, "rating": 1500, "tags": ["constructive algorithms", "games", "implementation", "math"]}, "author": {"contestId": 1737, "members": [{"handle": "StaneLegend"}], "participantType": "PRACTICE", "ghost": false, "startTimeSeconds": 1665153300}, "programmingLanguage": "GNU C++20 (64)", "verdict": "WRONG_ANSWER", "testset": "TESTS", "passedTestCount": 2, "timeConsumedMillis": 30, "memoryConsumedBytes": 0}, {"id": 175066400, "contestId": 1737, "creationTimeSeconds": 1665198714, "relativeTimeSeconds": 2147483647, "problem": {"contestId": 1737, "index": "C", "name": "Ela and Crickets", "type": "PROGRAMMING", "points": 1500.0, "rating": 1500, "tags": ["constructive algorithms", "games", "implementation", "math"]}, "author": {"contestId": 1737, "members": [{"handle": "StaneLegend"}], "participantType": "PRACTICE", "ghost": false, "startTimeSeconds": 1665153300}, "programmingLanguage": "GNU C++20 (64)", "verdict": "WRONG_ANSWER", "testset": "TESTS", "passedTestCount": 2, "timeConsumedMillis": 46, "memoryConsumedBytes": 0}, {"id": 175066360, "contestId": 1737, "creationTimeSeconds": 1665198655, "relativeTimeSeconds": 2147483647, "problem": {"contestId": 1737, "index": "C", "name": "Ela and Crickets", "type": "PROGRAMMING", "points": 1500.0, "rating": 1500, "tags": ["constructive algorithms", "games", "implementation", "math"]}, "author": {"contestId": 1737, "members": [{"handle": "StaneLegend"}], "participantType": "PRACTICE", "ghost": false, "startTimeSeconds": 1665153300}, "programmingLanguage": "GNU C++20 (64)", "verdict": "WRONG_ANSWER", "testset": "TESTS", "passedTestCount": 2, "timeConsumedMillis": 46, "memoryConsumedBytes": 0}, {"id": 175066346, "contestId": 1737, "creationTimeSeconds": 1665198639, "relativeTimeSeconds": 2147483647, "problem": {"contestId": 1737, "index": "C", "name": "Ela and Crickets", "type": "PROGRAMMING", "points": 1500.0, "rating": 1500, "tags": ["constructive algorithms", "games", "implementation", "math"]}, "author": {"contestId": 1737, "members": [{"handle": "StaneLegend"}], "participantType": "PRACTICE", "ghost": false, "startTimeSeconds": 1665153300}, "programmingLanguage": "GNU C++20 (64)", "verdict": "WRONG_ANSWER", "testset": "TESTS", "passedTestCount": 0, "timeConsumedMillis": 0, "memoryConsumedBytes": 0}, {"id": 175066313, "contestId": 1737, "creationTimeSeconds": 1665198594, "relativeTimeSeconds": 2147483647, "problem": {"contestId": 1737, "index": "C", "name": "Ela and Crickets", "type": "PROGRAMMING", "points": 1500.0, "rating": 1500, "tags": ["constructive algorithms", "games", "implementation", "math"]}, "author": {"contestId": 1737, "members": [{"handle": "StaneLegend"}], "participantType": "PRACTICE", "ghost": false, "startTimeSeconds": 1665153300}, "programmingLanguage": "GNU C++20 (64)", "verdict": "WRONG_ANSWER", "testset": "TESTS", "passedTestCount": 2, "timeConsumedMillis": 30, "memoryConsumedBytes": 0}, {"id": 175066213, "contestId": 1737, "creationTimeSeconds": 1665198463, "relativeTimeSeconds": 2147483647, "problem": {"contestId": 1737, "index": "C", "name": "Ela and Crickets", "type": "PROGRAMMING", "points": 1500.0, "rating": 1500, "tags": ["constructive algorithms", "games", "implementation", "math"]}, "author": {"contestId": 1737, "members": [{"handle": "StaneLegend"}], "participantType": "PRACTICE", "ghost": false, "startTimeSeconds": 1665153300}, "programmingLanguage": "GNU C++20 (64)", "verdict": "WRONG_ANSWER", "testset": "TESTS", "passedTestCount": 2, "timeConsumedMillis": 15, "memoryConsumedBytes": 0}, {"id": 175066156, "contestId": 1737, "creationTimeSeconds": 1665198374, "relativeTimeSeconds": 2147483647, "problem": {"contestId": 1737, "index": "C", "name": "Ela and Crickets", "type": "PROGRAMMING", "points": 1500.0, "rating": 1500, "tags": ["constructive algorithms", "games", "implementation", "math"]}, "author": {"contestId": 1737, "members": [{"handle": "StaneLegend"}], "participantType": "PRACTICE", "ghost": false, "startTimeSeconds": 1665153300}, "programmingLanguage": "GNU C++20 (64)", "verdict": "WRONG_ANSWER", "testset": "TESTS", "passedTestCount": 2, "timeConsumedMillis": 31, "memoryConsumedBytes": 0}, {"id": 175062203, "contestId": 1737, "creationTimeSeconds": 1665192098, "relativeTimeSeconds": 2147483647, "problem": {"contestId": 1737, "index": "E", "name": "Ela Goes Hiking", "type": "PROGRAMMING", "points": 2750.0, "rating": 2500, "tags": ["combinatorics", "dp", "math", "probabilities"]}, "author": {"contestId": 1737, "members": [{"handle": "StaneLegend"}], "participantType": "PRACTICE", "ghost": false, "startTimeSeconds": 1665153300}, "programmingLanguage": "GNU C++20 (64)", "verdict": "OK", "testset": "TESTS", "passedTestCount": 92, "timeConsumedMillis": 577, "memoryConsumedBytes": 48025600}, {"id": 175006844, "contestId": 1737, "creationTimeSeconds": 1665157434, "relativeTimeSeconds": 4134, "problem": {"contestId": 1737, "index": "D", "name": "Ela and the Wiring Wizard", "type": "PROGRAMMING", "points": 2000.0, "rating": 2200, "tags": ["brute force", "dp", "graphs", "greedy", "implementation", "shortest paths"]}, "author": {"contestId": 1737, "members": [{"handle": "StaneLegend"}], "participantType": "CONTESTANT", "ghost": false, "room": 154, "startTimeSeconds": 1665153300}, "programmingLanguage": "GNU C++20 (64)", "verdict": "OK", "testset": "TESTS", "passedTestCount": 38, "timeConsumedMillis": 810, "memoryConsumedBytes": 11878400}, {"id": 174997322, "contestId": 1737, "creationTimeSeconds": 1665155764, "relativeTimeSeconds": 2464, "problem": {"contestId": 1737, "index": "C", "name": "Ela and Crickets", "type": "PROGRAMMING", "points": 1500.0, "rating": 1500, "tags": ["constructive algorithms", "games", "implementation", "math"]}, "author": {"contestId": 1737, "members": [{"handle": "StaneLegend"}], "participantType": "CONTESTANT", "ghost": false, "room": 154, "startTimeSeconds": 1665153300}, "programmingLanguage": "GNU C++20 (64)", "verdict": "WRONG_ANSWER", "testset": "PRETESTS", "passedTestCount": 2, "timeConsumedMillis": 15, "memoryConsumedBytes": 0}, {"id": 174988119, "contestId": 1737, "creationTimeSeconds": 1665154332, "relativeTimeSeconds": 1032, "problem": {"contestId": 1737, "index": "B", "name": "Ela's Fitness and the Luxury Number", "type": "PROGRAMMING", "points": 1000.0, "rating": 1300, "tags": ["binary search", "implementation", "math"]}, "author": {"contestId": 1737, "members": [{"handle": "StaneLegend"}], "participantType": "CONTESTANT", "ghost": false, "room": 154, "startTimeSeconds": 1665153300}, "programmingLanguage": "GNU C++20 (64)", "verdict": "OK", "testset": "TESTS", "passedTestCount": 17, "timeConsumedMillis": 46, "memoryConsumedBytes": 0}, {"id": 174983395, "contestId": 1737, "creationTimeSeconds": 1665153598, "relativeTimeSeconds": 298, "problem": {"contestId": 1737, "index": "A", "name": "Ela Sorting Books", "type": "PROGRAMMING", "points": 500.0, "rating": 900, "tags": ["greedy", "implementation", "strings"]}, "author": {"contestId": 1737, "members": [{"handle": "StaneLegend"}], "participantType": "CONTESTANT", "ghost": false, "room": 154, "startTimeSeconds": 1665153300}, "programmingLanguage": "GNU C++20 (64)", "verdict": "OK", "testset": "TESTS", "passedTestCount": 13, "timeConsumedMillis": 15, "memoryConsumedBytes": 0}, {"id": 174137351, "contestId": 1738, "creationTimeSeconds": 1664554566, "relativeTimeSeconds": 6066, "problem": {"contestId": 1738, "index": "F", "name": "Connectivity Addicts", "type": "PROGRAMMING", "points": 2750.0, "rating": 2400, "tags": ["constructive algorithms", "dsu", "graphs", "greedy", "interactive", "shortest paths", "trees"]}, "author": {"contestId": 1738, "members": [{"handle": "StaneLegend"}], "participantType": "CONTESTANT", "ghost": false, "room": 394, "startTimeSeconds": 1664548500}, "programmingLanguage": "GNU C++20 (64)", "verdict": "OK", "testset": "TESTS", "passedTestCount": 93, "timeConsumedMillis": 46, "memoryConsumedBytes": 102400}, {"id": 174123285, "contestId": 1738, "creationTimeSeconds": 1664552532, "relativeTimeSeconds": 4032, "problem": {"contestId": 1738, "index": "E", "name": "Balance Addicts", "type": "PROGRAMMING", "points": 2500.0, "rating": 2300, "tags": ["combinatorics", "dp", "math", "two pointers"]}, "author": {"contestId": 1738, "members": [{"handle": "StaneLegend"}], "participantType": "CONTESTANT", "ghost": false, "room": 394, "startTimeSeconds": 1664548500}, "programmingLanguage": "GNU C++20 (64)", "verdict": "OK", "testset": "TESTS", "passedTestCount": 52, "timeConsumedMillis": 171, "memoryConsumedBytes": 12697600}, {"id": 174112746, "contestId": 1738, "creationTimeSeconds": 1664551283, "relativeTimeSeconds": 2783, "problem": {"contestId": 1738, "index": "D", "name": "Permutation Addicts", "type": "PROGRAMMING", "points": 2000.0, "rating": 1900, "tags": ["constructive algorithms", "data structures", "dfs and similar", "dsu", "graphs", "trees"]}, "author": {"contestId": 1738, "members": [{"handle": "StaneLegend"}], "participantType": "CONTESTANT", "ghost": false, "room": 394, "startTimeSeconds": 1664548500}, "programmingLanguage": "GNU C++20 (64)", "verdict": "OK", "testset": "TESTS", "passedTestCount": 52, "timeConsumedMillis": 171, "memoryConsumedBytes": 5017600}, {"id": 174098962, "contestId": 1738, "creationTimeSeconds": 1664549861, "relativeTimeSeconds": 1361, "problem": {"contestId": 1738, "index": "C", "name": "Even Number Addicts", "type": "PROGRAMMING", "points": 1500.0, "rating": 1500, "tags": ["dp", "games", "greedy", "math"]}, "author": {"contestId": 1738, "members": [{"handle": "StaneLegend"}], "participantType": "CONTESTANT", "ghost": false, "room": 394, "startTimeSeconds": 1664548500}, "programmingLanguage": "GNU C++20 (64)", "verdict": "OK", "testset": "TESTS", "passedTestCount": 78, "timeConsumedMillis": 31, "memoryConsumedBytes": 204800}, {"id": 174094361, "contestId": 1738, "creationTimeSeconds": 1664549377, "relativeTimeSeconds": 877, "problem": {"contestId": 1738, "index": "B", "name": "Prefix Sum Addicts", "type": "PROGRAMMING", "points": 1000.0, "rating": 1200, "tags": ["constructive algorithms", "greedy", "math", "sortings"]}, "author": {"contestId": 1738, "members": [{"handle": "StaneLegend"}], "participantType": "CONTESTANT", "ghost": false, "room": 394, "startTimeSeconds": 1664548500}, "programmingLanguage": "GNU C++20 (64)", "verdict": "OK", "testset": "TESTS", "passedTestCount": 92, "timeConsumedMillis": 218, "memoryConsumedBytes": 819200}, {"id": 174091786, "contestId": 1738, "creationTimeSeconds": 1664549076, "relativeTimeSeconds": 576, "problem": {"contestId": 1738, "index": "A", "name": "Glory Addicts", "type": "PROGRAMMING", "points": 500.0, "rating": 800, "tags": ["greedy", "implementation", "sortings"]}, "author": {"contestId": 1738, "members": [{"handle": "StaneLegend"}], "participantType": "CONTESTANT", "ghost": false, "room": 394, "startTimeSeconds": 1664548500}, "programmingLanguage": "GNU C++20 (64)", "verdict": "OK", "testset": "TESTS", "passedTestCount": 27, "timeConsumedMillis": 249, "memoryConsumedBytes": 3584000}, {"id": 158187762, "contestId": 1681, "creationTimeSeconds": 1653319033, "relativeTimeSeconds": 2533, "problem": {"contestId": 1681, "index": "F", "name": "Unique Occurrences", "type": "PROGRAMMING", "rating": 2300, "tags": ["data structures", "dfs and similar", "divide and conquer", "dp", "dsu", "trees"]}, "author": {"contestId": 1681, "members": [{"handle": "StaneLegend"}], "participantType": "CONTESTANT", "ghost": false, "startTimeSeconds": 1653316500}, "programmingLanguage": "GNU C++20 (64)", "verdict": "OK", "testset": "TESTS", "passedTestCount": 54, "timeConsumedMillis": 2713, "memoryConsumedBytes": 378060800}, {"id": 158083711, "contestId": 1682, "creationTimeSeconds": 1653241779, "relativeTimeSeconds": 2147483647, "problem": {"contestId": 1682, "index": "E", "name": "Unordered Swaps", "type": "PROGRAMMING", "points": 2500.0, "rating": 2700, "tags": ["constructive algorithms", "dfs and similar", "graphs", "greedy", "math", "sortings", "trees"]}, "author": {"contestId": 1682, "members": [{"handle": "StaneLegend"}], "participantType": "PRACTICE", "ghost": false, "startTimeSeconds": 1653230100}, "programmingLanguage": "GNU C++20 (64)", "verdict": "OK", "testset": "TESTS", "passedTestCount": 95, "timeConsumedMillis": 561, "memoryConsumedBytes": 39219200}, {"id": 158080642, "contestId": 1682, "creationTimeSeconds": 1653240068, "relativeTimeSeconds": 2147483647, "problem": {"contestId": 1682, "index": "D", "name": "Circular Spanning Tree", "type": "PROGRAMMING", "points": 2000.0, "rating": 2000, "tags": ["constructive algorithms", "implementation", "trees"]}, "author": {"contestId": 1682, "members": [{"handle": "StaneLegend"}], "participantType": "PRACTICE", "ghost": false, "startTimeSeconds": 1653230100}, "programmingLanguage": "GNU C++20 (64)", "verdict": "OK", "testset": "TESTS", "passedTestCount": 30, "timeConsumedMillis": 545, "memoryConsumedBytes": 1331200}, {"id": 158072078, "contestId": 1682, "creationTimeSeconds": 1653236719, "relativeTimeSeconds": 6619, "problem": {"contestId": 1682, "index": "E", "name": "Unordered Swaps", "type": "PROGRAMMING", "points": 2500.0, "rating": 2700, "tags": ["constructive algorithms", "dfs and similar", "graphs", "greedy", "math", "sortings", "trees"]}, "author": {"contestId": 1682, "members": [{"handle": "StaneLegend"}], "participantType": "OUT_OF_COMPETITION", "ghost": false, "room": 1006, "startTimeSeconds": 1653230100}, "programmingLanguage": "GNU C++20 (64)", "verdict": "WRONG_ANSWER", "testset": "PRETESTS", "passedTestCount": 1, "timeConsumedMillis": 15, "memoryConsumedBytes": 6553600}, {"id": 158055442, "contestId": 1682, "creationTimeSeconds": 1653234332, "relativeTimeSeconds": 4232, "problem": {"contestId": 1682, "index": "D", "name": "Circular Spanning Tree", "type": "PROGRAMMING", "points": 2000.0, "rating": 2000, "tags": ["constructive algorithms", "implementation", "trees"]}, "author": {"contestId": 1682, "members": [{"handle": "StaneLegend"}], "participantType": "OUT_OF_COMPETITION", "ghost": false, "room": 1006, "startTimeSeconds": 1653230100}, "programmingLanguage": "GNU C++20 (64)", "verdict": "WRONG_ANSWER", "testset": "PRETESTS", "passedTestCount": 1, "timeConsumedMillis": 264, "memoryConsumedBytes": 819200}, {"id": 158054796, "contestId": 1682, "creationTimeSeconds": 1653234253, "relativeTimeSeconds": 4153, "problem": {"contestId": 1682, "index": "D", "name": "Circular Spanning Tree", "type": "PROGRAMMING", "points": 2000.0, "rating": 2000, "tags": ["constructive algorithms", "implementation", "trees"]}, "author": {"contestId": 1682, "members": [{"handle": "StaneLegend"}], "participantType": "OUT_OF_COMPETITION", "ghost": false, "room": 1006, "startTimeSeconds": 1653230100}, "programmingLanguage": "GNU C++20 (64)", "verdict": "WRONG_ANSWER", "testset": "PRETESTS", "passedTestCount": 1, "timeConsumedMillis": 233, "memoryConsumedBytes": 819200}, {"id": 158054581, "contestId": 1682, "creationTimeSeconds": 1653234225, "relativeTimeSeconds": 4125, "problem": {"contestId": 1682, "index": "D", "name": "Circular Spanning Tree", "type": "PROGRAMMING", "points": 2000.0, "rating": 2000, "tags": ["constructive algorithms", "implementation", "trees"]}, "author": {"contestId": 1682, "members": [{"handle": "StaneLegend"}], "participantType": "OUT_OF_COMPETITION", "ghost": false, "room": 1006, "startTimeSeconds": 1653230100}, "programmingLanguage": "GNU C++20 (64)", "verdict": "WRONG_ANSWER", "testset": "PRETESTS", "passedTestCount": 0, "timeConsumedMillis": 0, "memoryConsumedBytes": 819200}, {"id": 158035827, "contestId": 1682, "creationTimeSeconds": 1653232418, "relativeTimeSeconds": 2318, "problem": {"contestId": 1682, "index": "D", "name": "Circular Spanning Tree", "type": "PROGRAMMING", "points": 2000.0, "rating": 2000, "tags": ["constructive algorithms", "implementation", "trees"]}, "author": {"contestId": 1682, "members": [{"handle": "StaneLegend"}], "participantType": "OUT_OF_COMPETITION", "ghost": false, "room": 1006, "startTimeSeconds": 1653230100}, "programmingLanguage": "GNU C++20 (64)", "verdict": "WRONG_ANSWER", "testset": "PRETESTS", "passedTestCount": 1, "timeConsumedMillis": 248, "memoryConsumedBytes": 819200}, {"id": 158035416, "contestId": 1682, "creationTimeSeconds": 1653232381, "relativeTimeSeconds": 2281, "problem": {"contestId": 1682, "index": "D", "name": "Circular Spanning Tree", "type": "PROGRAMMING", "points": 2000.0, "rating": 2000, "tags": ["constructive algorithms", "implementation", "trees"]}, "author": {"contestId": 1682, "members": [{"handle": "StaneLegend"}], "participantType": "OUT_OF_COMPETITION", "ghost": false, "room": 1006, "startTimeSeconds": 1653230100}, "programmingLanguage": "GNU C++20 (64)", "verdict": "WRONG_ANSWER", "testset": "PRETESTS", "passedTestCount": 0, "timeConsumedMillis": 0, "memoryConsumedBytes": 819200}, {"id": 158020317, "contestId": 1682, "creationTimeSeconds": 1653231307, "relativeTimeSeconds": 1207, "problem": {"contestId": 1682, "index": "C", "name": "LIS or Reverse LIS?", "type": "PROGRAMMING", "points": 1500.0, "rating": 1400, "tags": ["constructive algorithms", "greedy", "implementation", "math"]}, "author": {"contestId": 1682, "members": [{"handle": "StaneLegend"}], "participantType": "OUT_OF_COMPETITION", "ghost": false, "room": 1006, "startTimeSeconds": 1653230100}, "programmingLanguage": "GNU C++20 (64)", "verdict": "OK", "testset": "TESTS", "passedTestCount": 28, "timeConsumedMillis": 545, "memoryConsumedBytes": 10444800}, {"id": 158016762, "contestId": 1682, "creationTimeSeconds": 1653231083, "relativeTimeSeconds": 983, "problem": {"contestId": 1682, "index": "C", "name": "LIS or Reverse LIS?", "type": "PROGRAMMING", "points": 1500.0, "rating": 1400, "tags": ["constructive algorithms", "greedy", "implementation", "math"]}, "author": {"contestId": 1682, "members": [{"handle": "StaneLegend"}], "participantType": "OUT_OF_COMPETITION", "ghost": false, "room": 1006, "startTimeSeconds": 1653230100}, "programmingLanguage": "GNU C++20 (64)", "verdict": "WRONG_ANSWER", "testset": "PRETESTS", "passedTestCount": 1, "timeConsumedMillis": 93, "memoryConsumedBytes": 819200}, {"id": 158006496, "contestId": 1682, "creationTimeSeconds": 1653230454, "relativeTimeSeconds": 354, "problem": {"contestId": 1682, "index": "A", "name": "Palindromic Indices", "type": "PROGRAMMING", "points": 750.0, "rating": 800, "tags": ["greedy", "strings"]}, "author": {"contestId": 1682, "members": [{"handle": "StaneLegend"}], "participantType": "OUT_OF_COMPETITION", "ghost": false, "room": 1006, "startTimeSeconds": 1653230100}, "programmingLanguage": "GNU C++20 (64)", "verdict": "OK", "testset": "TESTS", "passedTestCount": 7, "timeConsumedMillis": 15, "memoryConsumedBytes": 512000}, {"id": 150263904, "contestId": 1654, "creationTimeSeconds": 1647782272, "relativeTimeSeconds": 6172, "problem": {"contestId": 1654, "index": "E", "name": "Arithmetic Operations", "type": "PROGRAMMING", "points": 2500.0, "rating": 2300, "tags": ["brute force", "data structures", "graphs", "math"]}, "author": {"contestId": 1654, "members": [{"handle": "StaneLegend"}], "participantType": "CONTESTANT", "ghost": false, "room": 50, "startTimeSeconds": 1647776100}, "programmingLanguage": "GNU C++20 (64)", "verdict": "OK", "testset": "TESTS", "passedTestCount": 71, "timeConsumedMillis": 4461, "memoryConsumedBytes": 41779200}, {"id": 150262884, "contestId": 1654, "creationTimeSeconds": 1647781959, "relativeTimeSeconds": 5859, "problem": {"contestId": 1654, "index": "E", "name": "Arithmetic Operations", "type": "PROGRAMMING", "points": 2500.0, "rating": 2300, "tags": ["brute force", "data structures", "graphs", "math"]}, "author": {"contestId": 1654, "members": [{"handle": "StaneLegend"}], "participantType": "CONTESTANT", "ghost": false, "room": 50, "startTimeSeconds": 1647776100}, "programmingLanguage": "GNU C++20 (64)", "verdict": "SKIPPED", "testset": "TESTS", "passedTestCount": 25, "timeConsumedMillis": 4258, "memoryConsumedBytes": 41267200}, {"id": 150262371, "contestId": 1654, "creationTimeSeconds": 1647781814, "relativeTimeSeconds": 5714, "problem": {"contestId": 1654, "index": "E", "name": "Arithmetic Operations", "type": "PROGRAMMING", "points": 2500.0, "rating": 2300, "tags": ["brute force", "data structures", "graphs", "math"]}, "author": {"contestId": 1654, "members": [{"handle": "StaneLegend"}], "participantType": "CONTESTANT", "ghost": false, "room": 50, "startTimeSeconds": 1647776100}, "programmingLanguage": "GNU C++20 (64)", "verdict": "TIME_LIMIT_EXCEEDED", "testset": "PRETESTS", "passedTestCount": 16, "timeConsumedMillis": 5000, "memoryConsumedBytes": 25190400}, {"id": 150261590, "contestId": 1654, "creationTimeSeconds": 1647781595, "relativeTimeSeconds": 5494, "problem": {"contestId": 1654, "index": "E", "name": "Arithmetic Operations", "type": "PROGRAMMING", "points": 2500.0, "rating": 2300, "tags": ["brute force", "data structures", "graphs", "math"]}, "author": {"contestId": 1654, "members": [{"handle": "StaneLegend"}], "participantType": "CONTESTANT", "ghost": false, "room": 50, "startTimeSeconds": 1647776100}, "programmingLanguage": "GNU C++20 (64)", "verdict": "TIME_LIMIT_EXCEEDED", "testset": "PRETESTS", "passedTestCount": 8, "timeConsumedMillis": 5000, "memoryConsumedBytes": 10342400}, {"id": 150252740, "contestId": 1654, "creationTimeSeconds": 1647779196, "relativeTimeSeconds": 3096, "problem": {"contestId": 1654, "index": "D", "name": "Potion Brewing Class", "type": "PROGRAMMING", "points": 2000.0, "rating": 2100, "tags": ["dfs and similar", "math", "number theory", "trees"]}, "author": {"contestId": 1654, "members": [{"handle": "StaneLegend"}], "participantType": "CONTESTANT", "ghost": false, "room": 50, "startTimeSeconds": 1647776100}, "programmingLanguage": "GNU C++17", "verdict": "OK", "testset": "TESTS", "passedTestCount": 29, "timeConsumedMillis": 623, "memoryConsumedBytes": 47923200}, {"id": 150244428, "contestId": 1654, "creationTimeSeconds": 1647777514, "relativeTimeSeconds": 1414, "problem": {"contestId": 1654, "index": "C", "name": "Alice and the Cake", "type": "PROGRAMMING", "points": 1250.0, "rating": 1400, "tags": ["data structures", "greedy", "implementation", "sortings"]}, "author": {"contestId": 1654, "members": [{"handle": "StaneLegend"}], "participantType": "CONTESTANT", "ghost": false, "room": 50, "startTimeSeconds": 1647776100}, "programmingLanguage": "GNU C++17", "verdict": "OK", "testset": "TESTS", "passedTestCount": 20, "timeConsumedMillis": 265, "memoryConsumedBytes": 24371200}, {"id": 150236655, "contestId": 1654, "creationTimeSeconds": 1647776669, "relativeTimeSeconds": 568, "problem": {"contestId": 1654, "index": "B", "name": "Prefix Removals", "type": "PROGRAMMING", "points": 750.0, "rating": 800, "tags": ["strings"]}, "author": {"contestId": 1654, "members": [{"handle": "StaneLegend"}], "participantType": "CONTESTANT", "ghost": false, "room": 50, "startTimeSeconds": 1647776100}, "programmingLanguage": "GNU C++17", "verdict": "OK", "testset": "TESTS", "passedTestCount": 16, "timeConsumedMillis": 46, "memoryConsumedBytes": 512000}, {"id": 150233676, "contestId": 1654, "creationTimeSeconds": 1647776453, "relativeTimeSeconds": 353, "problem": {"contestId": 1654, "index": "A", "name": "Maximum Cake Tastiness", "type": "PROGRAMMING", "points": 500.0, "rating": 800, "tags": ["brute force", "greedy", "implementation", "sortings"]}, "author": {"contestId": 1654, "members": [{"handle": "StaneLegend"}], "participantType": "CONTESTANT", "ghost": false, "room": 50, "startTimeSeconds": 1647776100}, "programmingLanguage": "GNU C++17", "verdict": "OK", "testset": "TESTS", "passedTestCount": 9, "timeConsumedMillis": 171, "memoryConsumedBytes": 4096000}, {"id": 148613943, "contestId": 1648, "creationTimeSeconds": 1646575231, "relativeTimeSeconds": 2147483647, "problem": {"contestId": 1648, "index": "D", "name": "Serious Business", "type": "PROGRAMMING", "points": 2000.0, "rating": 2800, "tags": ["data structures", "divide and conquer", "dp", "implementation", "shortest paths"]}, "author": {"contestId": 1648, "members": [{"handle": "StaneLegend"}], "participantType": "PRACTICE", "ghost": false, "startTimeSeconds": 1646560500}, "programmingLanguage": "GNU C++20 (64)", "verdict": "TIME_LIMIT_EXCEEDED", "testset": "TESTS", "passedTestCount": 9, "timeConsumedMillis": 5000, "memoryConsumedBytes": 449024000}, {"id": 148605479, "contestId": 1648, "creationTimeSeconds": 1646571477, "relativeTimeSeconds": 2147483647, "problem": {"contestId": 1648, "index": "D", "name": "Serious Business", "type": "PROGRAMMING", "points": 2000.0, "rating": 2800, "tags": ["data structures", "divide and conquer", "dp", "implementation", "shortest paths"]}, "author": {"contestId": 1648, "members": [{"handle": "StaneLegend"}], "participantType": "PRACTICE", "ghost": false, "startTimeSeconds": 1646560500}, "programmingLanguage": "GNU C++20 (64)", "verdict": "WRONG_ANSWER", "testset": "TESTS", "passedTestCount": 4, "timeConsumedMillis": 61, "memoryConsumedBytes": 192512000}, {"id": 148587121, "contestId": 1648, "creationTimeSeconds": 1646565932, "relativeTimeSeconds": 5432, "problem": {"contestId": 1648, "index": "B", "name": "Integral Array", "type": "PROGRAMMING", "points": 1000.0, "rating": 1800, "tags": ["brute force", "constructive algorithms", "data structures", "math"]}, "author": {"contestId": 1648, "members": [{"handle": "StaneLegend"}], "participantType": "CONTESTANT", "ghost": false, "room": 10, "startTimeSeconds": 1646560500}, "programmingLanguage": "GNU C++20 (64)", "verdict": "OK", "testset": "TESTS", "passedTestCount": 30, "timeConsumedMillis": 951, "memoryConsumedBytes": 15974400}, {"id": 148573779, "contestId": 1648, "creationTimeSeconds": 1646563707, "relativeTimeSeconds": 3207, "problem": {"contestId": 1648, "index": "C", "name": "Tyler and Strings", "type": "PROGRAMMING", "points": 1500.0, "rating": 1900, "tags": ["combinatorics", "data structures", "implementation"]}, "author": {"contestId": 1648, "members": [{"handle": "StaneLegend"}], "participantType": "CONTESTANT", "ghost": false, "room": 10, "startTimeSeconds": 1646560500}, "programmingLanguage": "GNU C++17", "verdict": "OK", "testset": "TESTS", "passedTestCount": 65, "timeConsumedMillis": 436, "memoryConsumedBytes": 16076800}, {"id": 148572751, "contestId": 1648, "creationTimeSeconds": 1646563560, "relativeTimeSeconds": 3060, "problem": {"contestId": 1648, "index": "C", "name": "Tyler and Strings", "type": "PROGRAMMING", "points": 1500.0, "rating": 1900, "tags": ["combinatorics", "data structures", "implementation"]}, "author": {"contestId": 1648, "members": [{"handle": "StaneLegend"}], "participantType": "CONTESTANT", "ghost": false, "room": 10, "startTimeSeconds": 1646560500}, "programmingLanguage": "GNU C++17", "verdict": "WRONG_ANSWER", "testset": "PRETESTS", "passedTestCount": 4, "timeConsumedMillis": 78, "memoryConsumedBytes": 16076800}, {"id": 148556723, "contestId": 1648, "creationTimeSeconds": 1646561764, "relativeTimeSeconds": 1264, "problem": {"contestId": 1648, "index": "A", "name": "Weird Sum", "type": "PROGRAMMING", "points": 500.0, "rating": 1400, "tags": ["combinatorics", "data structures", "geometry", "math", "matrices", "sortings"]}, "author": {"contestId": 1648, "members": [{"handle": "StaneLegend"}], "participantType": "CONTESTANT", "ghost": false, "room": 10, "startTimeSeconds": 1646560500}, "programmingLanguage": "GNU C++17", "verdict": "OK", "testset": "TESTS", "passedTestCount": 65, "timeConsumedMillis": 280, "memoryConsumedBytes": 17100800}, {"id": 141597352, "contestId": 1621, "creationTimeSeconds": 1641265857, "relativeTimeSeconds": 7317, "problem": {"contestId": 1621, "index": "E", "name": "New School", "type": "PROGRAMMING", "points": 2250.0, "rating": 2300, "tags": ["binary search", "data structures", "dp", "greedy", "implementation", "sortings"]}, "author": {"contestId": 1621, "members": [{"handle": "StaneLegend"}], "participantType": "VIRTUAL", "ghost": false, "startTimeSeconds": 1641258540}, "programmingLanguage": "GNU C++17", "verdict": "OK", "testset": "TESTS", "passedTestCount": 36, "timeConsumedMillis": 218, "memoryConsumedBytes": 11673600}, {"id": 141597101, "contestId": 1621, "creationTimeSeconds": 1641265470, "relativeTimeSeconds": 6930, "problem": {"contestId": 1621, "index": "E", "name": "New School", "type": "PROGRAMMING", "points": 2250.0, "rating": 2300, "tags": ["binary search", "data structures", "dp", "greedy", "implementation", "sortings"]}, "author": {"contestId": 1621, "members": [{"handle": "StaneLegend"}], "participantType": "VIRTUAL", "ghost": false, "startTimeSeconds": 1641258540}, "programmingLanguage": "GNU C++17", "verdict": "WRONG_ANSWER", "testset": "TESTS", "passedTestCount": 1, "timeConsumedMillis": 0, "memoryConsumedBytes": 5324800}, {"id": 141595751, "contestId": 1621, "creationTimeSeconds": 1641263180, "relativeTimeSeconds": 4640, "problem": {"contestId": 1621, "index": "D", "name": "The Winter Hike", "type": "PROGRAMMING", "points": 1750.0, "rating": 2100, "tags": ["constructive algorithms", "greedy", "math"]}, "author": {"contestId": 1621, "members": [{"handle": "StaneLegend"}], "participantType": "VIRTUAL", "ghost": false, "startTimeSeconds": 1641258540}, "programmingLanguage": "GNU C++17", "verdict": "OK", "testset": "TESTS", "passedTestCount": 5, "timeConsumedMillis": 62, "memoryConsumedBytes": 2048000}, {"id": 141594671, "contestId": 1621, "creationTimeSeconds": 1641261212, "relativeTimeSeconds": 2672, "problem": {"contestId": 1621, "index": "C", "name": "Hidden Permutations", "type": "PROGRAMMING", "points": 1500.0, "rating": 1700, "tags": ["dfs and similar", "interactive", "math"]}, "author": {"contestId": 1621, "members": [{"handle": "StaneLegend"}], "participantType": "VIRTUAL", "ghost": false, "startTimeSeconds": 1641258540}, "programmingLanguage": "GNU C++17", "verdict": "OK", "testset": "TESTS", "passedTestCount": 23, "timeConsumedMillis": 156, "memoryConsumedBytes": 102400}, {"id": 141594622, "contestId": 1621, "creationTimeSeconds": 1641261114, "relativeTimeSeconds": 2574, "problem": {"contestId": 1621, "index": "C", "name": "Hidden Permutations", "type": "PROGRAMMING", "points": 1500.0, "rating": 1700, "tags": ["dfs and similar", "interactive", "math"]}, "author": {"contestId": 1621, "members": [{"handle": "StaneLegend"}], "participantType": "VIRTUAL", "ghost": false, "startTimeSeconds": 1641258540}, "programmingLanguage": "GNU C++17", "verdict": "IDLENESS_LIMIT_EXCEEDED", "testset": "TESTS", "passedTestCount": 0, "timeConsumedMillis": 0, "memoryConsumedBytes": 0}, {"id": 141593902, "contestId": 1621, "creationTimeSeconds": 1641259501, "relativeTimeSeconds": 961, "problem": {"contestId": 1621, "index": "B", "name": "Integers Shop", "type": "PROGRAMMING", "points": 1000.0, "rating": 1500, "tags": ["data structures", "greedy", "implementation"]}, "author": {"contestId": 1621, "members": [{"handle": "StaneLegend"}], "participantType": "VIRTUAL", "ghost": false, "startTimeSeconds": 1641258540}, "programmingLanguage": "GNU C++17", "verdict": "OK", "testset": "TESTS", "passedTestCount": 19, "timeConsumedMillis": 202, "memoryConsumedBytes": 2457600}, {"id": 141593748, "contestId": 1621, "creationTimeSeconds": 1641259170, "relativeTimeSeconds": 630, "problem": {"contestId": 1621, "index": "B", "name": "Integers Shop", "type": "PROGRAMMING", "points": 1000.0, "rating": 1500, "tags": ["data structures", "greedy", "implementation"]}, "author": {"contestId": 1621, "members": [{"handle": "StaneLegend"}], "participantType": "VIRTUAL", "ghost": false, "startTimeSeconds": 1641258540}, "programmingLanguage": "GNU C++17", "verdict": "WRONG_ANSWER", "testset": "TESTS", "passedTestCount": 1, "timeConsumedMillis": 202, "memoryConsumedBytes": 2457600}, {"id": 141593592, "contestId": 1621, "creationTimeSeconds": 1641258742, "relativeTimeSeconds": 202, "problem": {"contestId": 1621, "index": "A", "name": "Stable Arrangement of Rooks", "type": "PROGRAMMING", "points": 500.0, "rating": 800, "tags": ["constructive algorithms"]}, "author": {"contestId": 1621, "members": [{"handle": "StaneLegend"}], "participantType": "VIRTUAL", "ghost": false, "startTimeSeconds": 1641258540}, "programmingLanguage": "GNU C++17", "verdict": "OK", "testset": "TESTS", "passedTestCount": 5, "timeConsumedMillis": 0, "memoryConsumedBytes": 102400}, {"id": 138836690, "contestId": 1608, "creationTimeSeconds": 1639294974, "relativeTimeSeconds": 3894, "problem": {"contestId": 1608, "index": "D", "name": "Dominoes", "type": "PROGRAMMING", "points": 1500.0, "rating": 2400, "tags": ["combinatorics", "fft", "graphs", "math", "number theory"]}, "author": {"contestId": 1608, "members": [{"handle": "StaneLegend"}], "participantType": "VIRTUAL", "ghost": false, "startTimeSeconds": 1639291080}, "programmingLanguage": "GNU C++17", "verdict": "OK", "testset": "TESTS", "passedTestCount": 50, "timeConsumedMillis": 296, "memoryConsumedBytes": 16793600}, {"id": 138834631, "contestId": 1608, "creationTimeSeconds": 1639293004, "relativeTimeSeconds": 1924, "problem": {"contestId": 1608, "index": "C", "name": "Game Master", "type": "PROGRAMMING", "points": 1000.0, "rating": 1700, "tags": ["data structures", "dfs and similar", "dp", "graphs", "greedy", "two pointers"]}, "author": {"contestId": 1608, "members": [{"handle": "StaneLegend"}], "participantType": "VIRTUAL", "ghost": false, "startTimeSeconds": 1639291080}, "programmingLanguage": "GNU C++17", "verdict": "OK", "testset": "TESTS", "passedTestCount": 50, "timeConsumedMillis": 93, "memoryConsumedBytes": 5222400}, {"id": 138833541, "contestId": 1608, "creationTimeSeconds": 1639291925, "relativeTimeSeconds": 845, "problem": {"contestId": 1608, "index": "B", "name": "Build the Permutation", "type": "PROGRAMMING", "points": 750.0, "rating": 1200, "tags": ["constructive algorithms", "greedy"]}, "author": {"contestId": 1608, "members": [{"handle": "StaneLegend"}], "participantType": "VIRTUAL", "ghost": false, "startTimeSeconds": 1639291080}, "programmingLanguage": "GNU C++17", "verdict": "OK", "testset": "TESTS", "passedTestCount": 9, "timeConsumedMillis": 31, "memoryConsumedBytes": 0}, {"id": 138832777, "contestId": 1608, "creationTimeSeconds": 1639291192, "relativeTimeSeconds": 112, "problem": {"contestId": 1608, "index": "A", "name": "Find Array", "type": "PROGRAMMING", "points": 250.0, "rating": 800, "tags": ["constructive algorithms", "math"]}, "author": {"contestId": 1608, "members": [{"handle": "StaneLegend"}], "participantType": "VIRTUAL", "ghost": false, "startTimeSeconds": 1639291080}, "programmingLanguage": "GNU C++17", "verdict": "OK", "testset": "TESTS", "passedTestCount": 20, "timeConsumedMillis": 15, "memoryConsumedBytes": 0}, {"id": 138592440, "contestId": 1540, "creationTimeSeconds": 1639103189, "relativeTimeSeconds": 2369, "problem": {"contestId": 1540, "index": "B", "name": "Tree Array", "type": "PROGRAMMING", "points": 1250.0, "rating": 2300, "tags": ["brute force", "combinatorics", "dp", "graphs", "math", "probabilities", "trees"]}, "author": {"contestId": 1540, "members": [{"handle": "StaneLegend"}], "participantType": "VIRTUAL", "ghost": false, "startTimeSeconds": 1639100820}, "programmingLanguage": "GNU C++17", "verdict": "OK", "testset": "TESTS", "passedTestCount": 15, "timeConsumedMillis": 109, "memoryConsumedBytes": 512000}, {"id": 138591724, "contestId": 1540, "creationTimeSeconds": 1639101447, "relativeTimeSeconds": 627, "problem": {"contestId": 1540, "index": "A", "name": "Great Graphs", "type": "PROGRAMMING", "points": 500.0, "rating": 1400, "tags": ["constructive algorithms", "graphs", "greedy", "shortest paths", "sortings"]}, "author": {"contestId": 1540, "members": [{"handle": "StaneLegend"}], "participantType": "VIRTUAL", "ghost": false, "startTimeSeconds": 1639100820}, "programmingLanguage": "GNU C++17", "verdict": "OK", "testset": "TESTS", "passedTestCount": 13, "timeConsumedMillis": 46, "memoryConsumedBytes": 819200}, {"id": 136478130, "contestId": 1612, "creationTimeSeconds": 1637581600, "relativeTimeSeconds": 2147483647, "problem": {"contestId": 1612, "index": "G", "name": "Max Sum Array", "type": "PROGRAMMING", "rating": 2500, "tags": ["combinatorics", "constructive algorithms", "greedy", "sortings"]}, "author": {"contestId": 1612, "members": [{"handle": "StaneLegend"}], "participantType": "PRACTICE", "ghost": false, "startTimeSeconds": 1637573700}, "programmingLanguage": "GNU C++17", "verdict": "OK", "testset": "TESTS", "passedTestCount": 21, "timeConsumedMillis": 873, "memoryConsumedBytes": 96460800}, {"id": 136478099, "contestId": 1612, "creationTimeSeconds": 1637581588, "relativeTimeSeconds": 2147483647, "problem": {"contestId": 1612, "index": "F", "name": "Armor and Weapons", "type": "PROGRAMMING", "rating": 2800, "tags": ["brute force", "dp", "greedy", "shortest paths"]}, "author": {"contestId": 1612, "members": [{"handle": "StaneLegend"}], "participantType": "PRACTICE", "ghost": false, "startTimeSeconds": 1637573700}, "programmingLanguage": "GNU C++17", "verdict": "WRONG_ANSWER", "testset": "TESTS", "passedTestCount": 0, "timeConsumedMillis": 655, "memoryConsumedBytes": 96460800}, {"id": 136463744, "contestId": 1612, "creationTimeSeconds": 1637579769, "relativeTimeSeconds": 6069, "problem": {"contestId": 1612, "index": "F", "name": "Armor and Weapons", "type": "PROGRAMMING", "rating": 2800, "tags": ["brute force", "dp", "greedy", "shortest paths"]}, "author": {"contestId": 1612, "members": [{"handle": "StaneLegend"}], "participantType": "CONTESTANT", "ghost": false, "startTimeSeconds": 1637573700}, "programmingLanguage": "GNU C++17", "verdict": "OK", "testset": "TESTS", "passedTestCount": 110, "timeConsumedMillis": 561, "memoryConsumedBytes": 468070400}, {"id": 136461861, "contestId": 1612, "creationTimeSeconds": 1637579444, "relativeTimeSeconds": 5744, "problem": {"contestId": 1612, "index": "F", "name": "Armor and Weapons", "type": "PROGRAMMING", "rating": 2800, "tags": ["brute force", "dp", "greedy", "shortest paths"]}, "author": {"contestId": 1612, "members": [{"handle": "StaneLegend"}], "participantType": "CONTESTANT", "ghost": false, "startTimeSeconds": 1637573700}, "programmingLanguage": "GNU C++17", "verdict": "TIME_LIMIT_EXCEEDED", "testset": "TESTS", "passedTestCount": 6, "timeConsumedMillis": 2000, "memoryConsumedBytes": 509747200}, {"id": 136454702, "contestId": 1612, "creationTimeSeconds": 1637578169, "relativeTimeSeconds": 4469, "problem": {"contestId": 1612, "index": "F", "name": "Armor and Weapons", "type": "PROGRAMMING", "rating": 2800, "tags": ["brute force", "dp", "greedy", "shortest paths"]}, "author": {"contestId": 1612, "members": [{"handle": "StaneLegend"}], "participantType": "CONTESTANT", "ghost": false, "startTimeSeconds": 1637573700}, "programmingLanguage": "GNU C++17", "verdict": "WRONG_ANSWER", "testset": "TESTS", "passedTestCount": 7, "timeConsumedMillis": 249, "memoryConsumedBytes": 66150400}, {"id": 136449879, "contestId": 1612, "creationTimeSeconds": 1637577307, "relativeTimeSeconds": 3607, "problem": {"contestId": 1612, "index": "E", "name": "Messages", "type": "PROGRAMMING", "rating": 2000, "tags": ["brute force", "dp", "greedy", "probabilities", "sortings"]}, "author": {"contestId": 1612, "members": [{"handle": "StaneLegend"}], "participantType": "CONTESTANT", "ghost": false, "startTimeSeconds": 1637573700}, "programmingLanguage": "GNU C++17", "verdict": "OK", "testset": "TESTS", "passedTestCount": 175, "timeConsumedMillis": 780, "memoryConsumedBytes": 60006400}, {"id": 136440389, "contestId": 1612, "creationTimeSeconds": 1637575822, "relativeTimeSeconds": 2122, "problem": {"contestId": 1612, "index": "D", "name": "X-Magic Pair", "type": "PROGRAMMING", "rating": 1600, "tags": ["math", "number theory"]}, "author": {"contestId": 1612, "members": [{"handle": "StaneLegend"}], "participantType": "CONTESTANT", "ghost": false, "startTimeSeconds": 1637573700}, "programmingLanguage": "GNU C++20 (64)", "verdict": "OK", "testset": "TESTS", "passedTestCount": 22, "timeConsumedMillis": 46, "memoryConsumedBytes": 0}, {"id": 136434970, "contestId": 1612, "creationTimeSeconds": 1637575089, "relativeTimeSeconds": 1389, "problem": {"contestId": 1612, "index": "C", "name": "Chat Ban", "type": "PROGRAMMING", "rating": 1300, "tags": ["binary search", "math"]}, "author": {"contestId": 1612, "members": [{"handle": "StaneLegend"}], "participantType": "CONTESTANT", "ghost": false, "startTimeSeconds": 1637573700}, "programmingLanguage": "GNU C++20 (64)", "verdict": "OK", "testset": "TESTS", "passedTestCount": 3, "timeConsumedMillis": 46, "memoryConsumedBytes": 0}, {"id": 136429802, "contestId": 1612, "creationTimeSeconds": 1637574491, "relativeTimeSeconds": 791, "problem": {"contestId": 1612, "index": "B", "name": "Special Permutation", "type": "PROGRAMMING", "rating": 900, "tags": ["constructive algorithms", "greedy"]}, "author": {"contestId": 1612, "members": [{"handle": "StaneLegend"}], "participantType": "CONTESTANT", "ghost": false, "startTimeSeconds": 1637573700}, "programmingLanguage": "GNU C++20 (64)", "verdict": "OK", "testset": "TESTS", "passedTestCount": 7, "timeConsumedMillis": 15, "memoryConsumedBytes": 0}, {"id": 136429212, "contestId": 1612, "creationTimeSeconds": 1637574427, "relativeTimeSeconds": 727, "problem": {"contestId": 1612, "index": "B", "name": "Special Permutation", "type": "PROGRAMMING", "rating": 900, "tags": ["constructive algorithms", "greedy"]}, "author": {"contestId": 1612, "members": [{"handle": "StaneLegend"}], "participantType": "CONTESTANT", "ghost": false, "startTimeSeconds": 1637573700}, "programmingLanguage": "GNU C++20 (64)", "verdict": "WRONG_ANSWER", "testset": "TESTS", "passedTestCount": 0, "timeConsumedMillis": 15, "memoryConsumedBytes": 0}, {"id": 136424908, "contestId": 1612, "creationTimeSeconds": 1637574026, "relativeTimeSeconds": 326, "problem": {"contestId": 1612, "index": "A", "name": "Distance", "type": "PROGRAMMING", "rating": 800, "tags": ["brute force", "constructive algorithms"]}, "author": {"contestId": 1612, "members": [{"handle": "StaneLegend"}], "participantType": "CONTESTANT", "ghost": false, "startTimeSeconds": 1637573700}, "programmingLanguage": "GNU C++20 (64)", "verdict": "OK", "testset": "TESTS", "passedTestCount": 8, "timeConsumedMillis": 31, "memoryConsumedBytes": 0}, {"id": 133032273, "contestId": 1601, "creationTimeSeconds": 1635150876, "relativeTimeSeconds": 7176, "problem": {"contestId": 1601, "index": "C", "name": "Optimal Insertion", "type": "PROGRAMMING", "points": 2000.0, "rating": 2300, "tags": ["data structures", "divide and conquer", "dp", "greedy", "sortings"]}, "author": {"contestId": 1601, "members": [{"handle": "StaneLegend"}], "participantType": "CONTESTANT", "ghost": false, "room": 20, "startTimeSeconds": 1635143700}, "programmingLanguage": "GNU C++20 (64)", "verdict": "TIME_LIMIT_EXCEEDED", "testset": "PRETESTS", "passedTestCount": 13, "timeConsumedMillis": 3000, "memoryConsumedBytes": 139161600}, {"id": 133032220, "contestId": 1601, "creationTimeSeconds": 1635150868, "relativeTimeSeconds": 7168, "problem": {"contestId": 1601, "index": "C", "name": "Optimal Insertion", "type": "PROGRAMMING", "points": 2000.0, "rating": 2300, "tags": ["data structures", "divide and conquer", "dp", "greedy", "sortings"]}, "author": {"contestId": 1601, "members": [{"handle": "StaneLegend"}], "participantType": "CONTESTANT", "ghost": false, "room": 20, "startTimeSeconds": 1635143700}, "programmingLanguage": "GNU C++17 (64)", "verdict": "TIME_LIMIT_EXCEEDED", "testset": "PRETESTS", "passedTestCount": 13, "timeConsumedMillis": 3000, "memoryConsumedBytes": 139161600}, {"id": 133032157, "contestId": 1601, "creationTimeSeconds": 1635150860, "relativeTimeSeconds": 7160, "problem": {"contestId": 1601, "index": "C", "name": "Optimal Insertion", "type": "PROGRAMMING", "points": 2000.0, "rating": 2300, "tags": ["data structures", "divide and conquer", "dp", "greedy", "sortings"]}, "author": {"contestId": 1601, "members": [{"handle": "StaneLegend"}], "participantType": "CONTESTANT", "ghost": false, "room": 20, "startTimeSeconds": 1635143700}, "programmingLanguage": "GNU C++17", "verdict": "OK", "testset": "TESTS", "passedTestCount": 20, "timeConsumedMillis": 2573, "memoryConsumedBytes": 137932800}, {"id": 133032119, "contestId": 1601, "creationTimeSeconds": 1635150853, "relativeTimeSeconds": 7153, "problem": {"contestId": 1601, "index": "C", "name": "Optimal Insertion", "type": "PROGRAMMING", "points": 2000.0, "rating": 2300, "tags": ["data structures", "divide and conquer", "dp", "greedy", "sortings"]}, "author": {"contestId": 1601, "members": [{"handle": "StaneLegend"}], "participantType": "CONTESTANT", "ghost": false, "room": 20, "startTimeSeconds": 1635143700}, "programmingLanguage": "GNU C++14", "verdict": "SKIPPED", "testset": "TESTS", "passedTestCount": 16, "timeConsumedMillis": 2620, "memoryConsumedBytes": 137932800}, {"id": 133031327, "contestId": 1601, "creationTimeSeconds": 1635150691, "relativeTimeSeconds": 6991, "problem": {"contestId": 1601, "index": "C", "name": "Optimal Insertion", "type": "PROGRAMMING", "points": 2000.0, "rating": 2300, "tags": ["data structures", "divide and conquer", "dp", "greedy", "sortings"]}, "author": {"contestId": 1601, "members": [{"handle": "StaneLegend"}], "participantType": "CONTESTANT", "ghost": false, "room": 20, "startTimeSeconds": 1635143700}, "programmingLanguage": "GNU C++20 (64)", "verdict": "TIME_LIMIT_EXCEEDED", "testset": "PRETESTS", "passedTestCount": 13, "timeConsumedMillis": 3000, "memoryConsumedBytes": 139161600}, {"id": 133031233, "contestId": 1601, "creationTimeSeconds": 1635150671, "relativeTimeSeconds": 6971, "problem": {"contestId": 1601, "index": "C", "name": "Optimal Insertion", "type": "PROGRAMMING", "points": 2000.0, "rating": 2300, "tags": ["data structures", "divide and conquer", "dp", "greedy", "sortings"]}, "author": {"contestId": 1601, "members": [{"handle": "StaneLegend"}], "participantType": "CONTESTANT", "ghost": false, "room": 20, "startTimeSeconds": 1635143700}, "programmingLanguage": "GNU C++17", "verdict": "SKIPPED", "testset": "TESTS", "passedTestCount": 16, "timeConsumedMillis": 2761, "memoryConsumedBytes": 137932800}, {"id": 133030912, "contestId": 1601, "creationTimeSeconds": 1635150588, "relativeTimeSeconds": 6888, "problem": {"contestId": 1601, "index": "C", "name": "Optimal Insertion", "type": "PROGRAMMING", "points": 2000.0, "rating": 2300, "tags": ["data structures", "divide and conquer", "dp", "greedy", "sortings"]}, "author": {"contestId": 1601, "members": [{"handle": "StaneLegend"}], "participantType": "CONTESTANT", "ghost": false, "room": 20, "startTimeSeconds": 1635143700}, "programmingLanguage": "GNU C++17", "verdict": "WRONG_ANSWER", "testset": "PRETESTS", "passedTestCount": 3, "timeConsumedMillis": 1575, "memoryConsumedBytes": 137932800}, {"id": 133026897, "contestId": 1601, "creationTimeSeconds": 1635150465, "relativeTimeSeconds": 6764, "problem": {"contestId": 1601, "index": "C", "name": "Optimal Insertion", "type": "PROGRAMMING", "points": 2000.0, "rating": 2300, "tags": ["data structures", "divide and conquer", "dp", "greedy", "sortings"]}, "author": {"contestId": 1601, "members": [{"handle": "StaneLegend"}], "participantType": "CONTESTANT", "ghost": false, "room": 20, "startTimeSeconds": 1635143700}, "programmingLanguage": "GNU C++17", "verdict": "WRONG_ANSWER", "testset": "PRETESTS", "passedTestCount": 3, "timeConsumedMillis": 1574, "memoryConsumedBytes": 137932800}, {"id": 133020543, "contestId": 1601, "creationTimeSeconds": 1635149883, "relativeTimeSeconds": 6183, "problem": {"contestId": 1601, "index": "C", "name": "Optimal Insertion", "type": "PROGRAMMING", "points": 2000.0, "rating": 2300, "tags": ["data structures", "divide and conquer", "dp", "greedy", "sortings"]}, "author": {"contestId": 1601, "members": [{"handle": "StaneLegend"}], "participantType": "CONTESTANT", "ghost": false, "room": 20, "startTimeSeconds": 1635143700}, "programmingLanguage": "GNU C++17", "verdict": "WRONG_ANSWER", "testset": "PRETESTS", "passedTestCount": 3, "timeConsumedMillis": 1544, "memoryConsumedBytes": 137932800}, {"id": 133019210, "contestId": 1601, "creationTimeSeconds": 1635149498, "relativeTimeSeconds": 5798, "problem": {"contestId": 1601, "index": "C", "name": "Optimal Insertion", "type": "PROGRAMMING", "points": 2000.0, "rating": 2300, "tags": ["data structures", "divide and conquer", "dp", "greedy", "sortings"]}, "author": {"contestId": 1601, "members": [{"handle": "StaneLegend"}], "participantType": "CONTESTANT", "ghost": false, "room": 20, "startTimeSeconds": 1635143700}, "programmingLanguage": "GNU C++20 (64)", "verdict": "WRONG_ANSWER", "testset": "PRETESTS", "passedTestCount": 3, "timeConsumedMillis": 2901, "memoryConsumedBytes": 275968000}, {"id": 133003481, "contestId": 1601, "creationTimeSeconds": 1635146683, "relativeTimeSeconds": 2983, "problem": {"contestId": 1601, "index": "B", "name": "Frog Traveler", "type": "PROGRAMMING", "points": 1250.0, "rating": 1900, "tags": ["data structures", "dfs and similar", "dp", "graphs", "shortest paths", "two pointers"]}, "author": {"contestId": 1601, "members": [{"handle": "StaneLegend"}], "participantType": "CONTESTANT", "ghost": false, "room": 20, "startTimeSeconds": 1635143700}, "programmingLanguage": "GNU C++20 (64)", "verdict": "OK", "testset": "TESTS", "passedTestCount": 50, "timeConsumedMillis": 873, "memoryConsumedBytes": 150732800}, {"id": 132999319, "contestId": 1601, "creationTimeSeconds": 1635145767, "relativeTimeSeconds": 2067, "problem": {"contestId": 1601, "index": "B", "name": "Frog Traveler", "type": "PROGRAMMING", "points": 1250.0, "rating": 1900, "tags": ["data structures", "dfs and similar", "dp", "graphs", "shortest paths", "two pointers"]}, "author": {"contestId": 1601, "members": [{"handle": "StaneLegend"}], "participantType": "CONTESTANT", "ghost": false, "room": 20, "startTimeSeconds": 1635143700}, "programmingLanguage": "GNU C++20 (64)", "verdict": "WRONG_ANSWER", "testset": "PRETESTS", "passedTestCount": 5, "timeConsumedMillis": 577, "memoryConsumedBytes": 96768000}, {"id": 132998630, "contestId": 1601, "creationTimeSeconds": 1635145632, "relativeTimeSeconds": 1932, "problem": {"contestId": 1601, "index": "B", "name": "Frog Traveler", "type": "PROGRAMMING", "points": 1250.0, "rating": 1900, "tags": ["data structures", "dfs and similar", "dp", "graphs", "shortest paths", "two pointers"]}, "author": {"contestId": 1601, "members": [{"handle": "StaneLegend"}], "participantType": "CONTESTANT", "ghost": false, "room": 20, "startTimeSeconds": 1635143700}, "programmingLanguage": "GNU C++20 (64)", "verdict": "WRONG_ANSWER", "testset": "PRETESTS", "passedTestCount": 0, "timeConsumedMillis": 30, "memoryConsumedBytes": 68915200}, {"id": 132988336, "contestId": 1601, "creationTimeSeconds": 1635144080, "relativeTimeSeconds": 380, "problem": {"contestId": 1601, "index": "A", "name": "Array Elimination", "type": "PROGRAMMING", "points": 500.0, "rating": 1300, "tags": ["bitmasks", "greedy", "math", "number theory"]}, "author": {"contestId": 1601, "members": [{"handle": "StaneLegend"}], "participantType": "CONTESTANT", "ghost": false, "room": 20, "startTimeSeconds": 1635143700}, "programmingLanguage": "GNU C++20 (64)", "verdict": "OK", "testset": "TESTS", "passedTestCount": 22, "timeConsumedMillis": 265, "memoryConsumedBytes": 2048000}, {"id": 132264337, "contestId": 1586, "creationTimeSeconds": 1634480609, "relativeTimeSeconds": 2147483647, "problem": {"contestId": 1586, "index": "E", "name": "Moment of Bloom", "type": "PROGRAMMING", "points": 2250.0, "rating": 2200, "tags": ["constructive algorithms", "dfs and similar", "dsu", "graph matchings", "graphs", "greedy", "trees"]}, "author": {"contestId": 1586, "members": [{"handle": "StaneLegend"}], "participantType": "PRACTICE", "ghost": false, "startTimeSeconds": 1634468700}, "programmingLanguage": "GNU C++20 (64)", "verdict": "OK", "testset": "TESTS", "passedTestCount": 43, "timeConsumedMillis": 577, "memoryConsumedBytes": 43008000}, {"id": 132245159, "contestId": 1586, "creationTimeSeconds": 1634473517, "relativeTimeSeconds": 4817, "problem": {"contestId": 1586, "index": "D", "name": "Omkar and the Meaning of Life", "type": "PROGRAMMING", "points": 1750.0, "rating": 1800, "tags": ["constructive algorithms", "greedy", "interactive", "math"]}, "author": {"contestId": 1586, "members": [{"handle": "StaneLegend"}], "participantType": "CONTESTANT", "ghost": false, "room": 210, "startTimeSeconds": 1634468700}, "programmingLanguage": "GNU C++20 (64)", "verdict": "OK", "testset": "TESTS", "passedTestCount": 26, "timeConsumedMillis": 15, "memoryConsumedBytes": 0}, {"id": 132234572, "contestId": 1586, "creationTimeSeconds": 1634471589, "relativeTimeSeconds": 2889, "problem": {"contestId": 1586, "index": "C", "name": "Omkar and Determination", "type": "PROGRAMMING", "points": 1500.0, "rating": 1700, "tags": ["constructive algorithms", "dp", "greedy", "implementation", "two pointers"]}, "author": {"contestId": 1586, "members": [{"handle": "StaneLegend"}], "participantType": "CONTESTANT", "ghost": false, "room": 210, "startTimeSeconds": 1634468700}, "programmingLanguage": "GNU C++20 (64)", "verdict": "OK", "testset": "TESTS", "passedTestCount": 88, "timeConsumedMillis": 748, "memoryConsumedBytes": 117145600}, {"id": 132234387, "contestId": 1586, "creationTimeSeconds": 1634471555, "relativeTimeSeconds": 2855, "problem": {"contestId": 1586, "index": "C", "name": "Omkar and Determination", "type": "PROGRAMMING", "points": 1500.0, "rating": 1700, "tags": ["constructive algorithms", "dp", "greedy", "implementation", "two pointers"]}, "author": {"contestId": 1586, "members": [{"handle": "StaneLegend"}], "participantType": "CONTESTANT", "ghost": false, "room": 210, "startTimeSeconds": 1634468700}, "programmingLanguage": "GNU C++20 (64)", "verdict": "WRONG_ANSWER", "testset": "PRETESTS", "passedTestCount": 0, "timeConsumedMillis": 30, "memoryConsumedBytes": 81715200}, {"id": 132230733, "contestId": 1586, "creationTimeSeconds": 1634470997, "relativeTimeSeconds": 2297, "problem": {"contestId": 1586, "index": "C", "name": "Omkar and Determination", "type": "PROGRAMMING", "points": 1500.0, "rating": 1700, "tags": ["constructive algorithms", "dp", "greedy", "implementation", "two pointers"]}, "author": {"contestId": 1586, "members": [{"handle": "StaneLegend"}], "participantType": "CONTESTANT", "ghost": false, "room": 210, "startTimeSeconds": 1634468700}, "programmingLanguage": "GNU C++20 (64)", "verdict": "WRONG_ANSWER", "testset": "PRETESTS", "passedTestCount": 2, "timeConsumedMillis": 638, "memoryConsumedBytes": 94720000}, {"id": 132219466, "contestId": 1586, "creationTimeSeconds": 1634469553, "relativeTimeSeconds": 853, "problem": {"contestId": 1586, "index": "B", "name": "Omkar and Heavenly Tree", "type": "PROGRAMMING", "points": 1000.0, "rating": 1200, "tags": ["brute force", "constructive algorithms", "trees"]}, "author": {"contestId": 1586, "members": [{"handle": "StaneLegend"}], "participantType": "CONTESTANT", "ghost": false, "room": 210, "startTimeSeconds": 1634468700}, "programmingLanguage": "GNU C++20 (64)", "verdict": "OK", "testset": "TESTS", "passedTestCount": 30, "timeConsumedMillis": 234, "memoryConsumedBytes": 102400}, {"id": 132217080, "contestId": 1586, "creationTimeSeconds": 1634469333, "relativeTimeSeconds": 633, "problem": {"contestId": 1586, "index": "A", "name": "Windblume Ode", "type": "PROGRAMMING", "points": 500.0, "rating": 800, "tags": ["brute force", "constructive algorithms", "greedy", "math", "number theory"]}, "author": {"contestId": 1586, "members": [{"handle": "StaneLegend"}], "participantType": "CONTESTANT", "ghost": false, "room": 210, "startTimeSeconds": 1634468700}, "programmingLanguage": "GNU C++20 (64)", "verdict": "OK", "testset": "TESTS", "passedTestCount": 15, "timeConsumedMillis": 577, "memoryConsumedBytes": 17612800}, {"id": 132215767, "contestId": 1586, "creationTimeSeconds": 1634469213, "relativeTimeSeconds": 513, "problem": {"contestId": 1586, "index": "A", "name": "Windblume Ode", "type": "PROGRAMMING", "points": 500.0, "rating": 800, "tags": ["brute force", "constructive algorithms", "greedy", "math", "number theory"]}, "author": {"contestId": 1586, "members": [{"handle": "StaneLegend"}], "participantType": "CONTESTANT", "ghost": false, "room": 210, "startTimeSeconds": 1634468700}, "programmingLanguage": "GNU C++20 (64)", "verdict": "WRONG_ANSWER", "testset": "PRETESTS", "passedTestCount": 2, "timeConsumedMillis": 483, "memoryConsumedBytes": 17612800}, {"id": 131837456, "contestId": 1593, "creationTimeSeconds": 1634142274, "relativeTimeSeconds": 6574, "problem": {"contestId": 1593, "index": "D2", "name": "Half of Same", "type": "PROGRAMMING", "rating": 1900, "tags": ["brute force", "math", "number theory"]}, "author": {"contestId": 1593, "members": [{"handle": "StaneLegend"}], "participantType": "CONTESTANT", "ghost": false, "startTimeSeconds": 1634135700}, "programmingLanguage": "GNU C++17", "verdict": "OK", "testset": "TESTS", "passedTestCount": 59, "timeConsumedMillis": 811, "memoryConsumedBytes": 7987200}, {"id": 131805562, "contestId": 1593, "creationTimeSeconds": 1634139332, "relativeTimeSeconds": 3632, "problem": {"contestId": 1593, "index": "F", "name": "Red-Black Number", "type": "PROGRAMMING", "rating": 2100, "tags": ["dfs and similar", "dp", "implementation", "math", "meet-in-the-middle"]}, "author": {"contestId": 1593, "members": [{"handle": "StaneLegend"}], "participantType": "CONTESTANT", "ghost": false, "startTimeSeconds": 1634135700}, "programmingLanguage": "GNU C++17", "verdict": "OK", "testset": "TESTS", "passedTestCount": 21, "timeConsumedMillis": 202, "memoryConsumedBytes": 200396800}, {"id": 131795369, "contestId": 1593, "creationTimeSeconds": 1634138552, "relativeTimeSeconds": 2852, "problem": {"contestId": 1593, "index": "E", "name": "Gardener and Tree", "type": "PROGRAMMING", "rating": 1600, "tags": ["brute force", "data structures", "dfs and similar", "greedy", "implementation", "trees"]}, "author": {"contestId": 1593, "members": [{"handle": "StaneLegend"}], "participantType": "CONTESTANT", "ghost": false, "startTimeSeconds": 1634135700}, "programmingLanguage": "GNU C++17", "verdict": "OK", "testset": "TESTS", "passedTestCount": 36, "timeConsumedMillis": 654, "memoryConsumedBytes": 64307200}, {"id": 131774563, "contestId": 1593, "creationTimeSeconds": 1634137191, "relativeTimeSeconds": 1491, "problem": {"contestId": 1593, "index": "D1", "name": "All are Same", "type": "PROGRAMMING", "rating": 1100, "tags": ["math", "number theory"]}, "author": {"contestId": 1593, "members": [{"handle": "StaneLegend"}], "participantType": "CONTESTANT", "ghost": false, "startTimeSeconds": 1634135700}, "programmingLanguage": "GNU C++17", "verdict": "OK", "testset": "TESTS", "passedTestCount": 53, "timeConsumedMillis": 15, "memoryConsumedBytes": 0}, {"id": 131770227, "contestId": 1593, "creationTimeSeconds": 1634136937, "relativeTimeSeconds": 1237, "problem": {"contestId": 1593, "index": "C", "name": "Save More Mice", "type": "PROGRAMMING", "rating": 1000, "tags": ["binary search", "greedy", "greedy"]}, "author": {"contestId": 1593, "members": [{"handle": "StaneLegend"}], "participantType": "CONTESTANT", "ghost": false, "startTimeSeconds": 1634135700}, "programmingLanguage": "GNU C++17", "verdict": "OK", "testset": "TESTS", "passedTestCount": 56, "timeConsumedMillis": 171, "memoryConsumedBytes": 3174400}, {"id": 131761912, "contestId": 1593, "creationTimeSeconds": 1634136479, "relativeTimeSeconds": 779, "problem": {"contestId": 1593, "index": "B", "name": "Make it Divisible by 25", "type": "PROGRAMMING", "rating": 900, "tags": ["dfs and similar", "dp", "greedy", "math", "math"]}, "author": {"contestId": 1593, "members": [{"handle": "StaneLegend"}], "participantType": "CONTESTANT", "ghost": false, "startTimeSeconds": 1634135700}, "programmingLanguage": "GNU C++17", "verdict": "OK", "testset": "TESTS", "passedTestCount": 3, "timeConsumedMillis": 249, "memoryConsumedBytes": 102400}, {"id": 131748626, "contestId": 1593, "creationTimeSeconds": 1634135856, "relativeTimeSeconds": 156, "problem": {"contestId": 1593, "index": "A", "name": "Elections", "type": "PROGRAMMING", "rating": 800, "tags": ["math"]}, "author": {"contestId": 1593, "members": [{"handle": "StaneLegend"}], "participantType": "CONTESTANT", "ghost": false, "startTimeSeconds": 1634135700}, "programmingLanguage": "GNU C++17", "verdict": "OK", "testset": "TESTS", "passedTestCount": 3, "timeConsumedMillis": 93, "memoryConsumedBytes": 0}, {"id": 131449497, "contestId": 1598, "creationTimeSeconds": 1633863321, "relativeTimeSeconds": 6621, "problem": {"contestId": 1598, "index": "F", "name": "RBS", "type": "PROGRAMMING", "rating": 2400, "tags": ["binary search", "bitmasks", "brute force", "data structures", "dp"]}, "author": {"contestId": 1598, "members": [{"handle": "StaneLegend"}], "participantType": "CONTESTANT", "ghost": false, "startTimeSeconds": 1633856700}, "programmingLanguage": "GNU C++17", "verdict": "OK", "testset": "TESTS", "passedTestCount": 123, "timeConsumedMillis": 171, "memoryConsumedBytes": 133734400}, {"id": 131447058, "contestId": 1598, "creationTimeSeconds": 1633862880, "relativeTimeSeconds": 6180, "problem": {"contestId": 1598, "index": "F", "name": "RBS", "type": "PROGRAMMING", "rating": 2400, "tags": ["binary search", "bitmasks", "brute force", "data structures", "dp"]}, "author": {"contestId": 1598, "members": [{"handle": "StaneLegend"}], "participantType": "CONTESTANT", "ghost": false, "startTimeSeconds": 1633856700}, "programmingLanguage": "GNU C++17", "verdict": "WRONG_ANSWER", "testset": "TESTS", "passedTestCount": 30, "timeConsumedMillis": 155, "memoryConsumedBytes": 133529600}, {"id": 131438342, "contestId": 1598, "creationTimeSeconds": 1633861461, "relativeTimeSeconds": 4761, "problem": {"contestId": 1598, "index": "E", "name": "Staircases", "type": "PROGRAMMING", "rating": 2100, "tags": ["brute force", "combinatorics", "data structures", "dfs and similar", "dp", "implementation", "math"]}, "author": {"contestId": 1598, "members": [{"handle": "StaneLegend"}], "participantType": "CONTESTANT", "ghost": false, "startTimeSeconds": 1633856700}, "programmingLanguage": "GNU C++17", "verdict": "OK", "testset": "TESTS", "passedTestCount": 44, "timeConsumedMillis": 140, "memoryConsumedBytes": 8806400}, {"id": 131410580, "contestId": 1598, "creationTimeSeconds": 1633857962, "relativeTimeSeconds": 1262, "problem": {"contestId": 1598, "index": "D", "name": "Training Session", "type": "PROGRAMMING", "rating": 1700, "tags": ["combinatorics", "data structures", "geometry", "implementation", "math"]}, "author": {"contestId": 1598, "members": [{"handle": "StaneLegend"}], "participantType": "CONTESTANT", "ghost": false, "startTimeSeconds": 1633856700}, "programmingLanguage": "GNU C++17", "verdict": "OK", "testset": "TESTS", "passedTestCount": 49, "timeConsumedMillis": 264, "memoryConsumedBytes": 14336000}, {"id": 131405721, "contestId": 1598, "creationTimeSeconds": 1633857463, "relativeTimeSeconds": 763, "problem": {"contestId": 1598, "index": "C", "name": "Delete Two Elements", "type": "PROGRAMMING", "rating": 1200, "tags": ["data structures", "dp", "implementation", "math", "two pointers"]}, "author": {"contestId": 1598, "members": [{"handle": "StaneLegend"}], "participantType": "CONTESTANT", "ghost": false, "startTimeSeconds": 1633856700}, "programmingLanguage": "GNU C++17", "verdict": "OK", "testset": "TESTS", "passedTestCount": 121, "timeConsumedMillis": 265, "memoryConsumedBytes": 25600000}, {"id": 131402188, "contestId": 1598, "creationTimeSeconds": 1633857124, "relativeTimeSeconds": 424, "problem": {"contestId": 1598, "index": "B", "name": "Groups", "type": "PROGRAMMING", "rating": 1000, "tags": ["brute force", "implementation"]}, "author": {"contestId": 1598, "members": [{"handle": "StaneLegend"}], "participantType": "CONTESTANT", "ghost": false, "startTimeSeconds": 1633856700}, "programmingLanguage": "GNU C++17", "verdict": "OK", "testset": "TESTS", "passedTestCount": 9, "timeConsumedMillis": 124, "memoryConsumedBytes": 3788800}, {"id": 131398516, "contestId": 1598, "creationTimeSeconds": 1633856850, "relativeTimeSeconds": 150, "problem": {"contestId": 1598, "index": "A", "name": "Computer Game", "type": "PROGRAMMING", "rating": 800, "tags": ["brute force", "dfs and similar", "dp", "implementation"]}, "author": {"contestId": 1598, "members": [{"handle": "StaneLegend"}], "participantType": "CONTESTANT", "ghost": false, "startTimeSeconds": 1633856700}, "programmingLanguage": "GNU C++17", "verdict": "OK", "testset": "TESTS", "passedTestCount": 7, "timeConsumedMillis": 15, "memoryConsumedBytes": 3686400}, {"id": 130368000, "contestId": 1581, "creationTimeSeconds": 1633003533, "relativeTimeSeconds": 6633, "problem": {"contestId": 1581, "index": "E", "name": "Train Maintenance", "type": "PROGRAMMING", "points": 2500.0, "rating": 2200, "tags": ["brute force", "data structures", "implementation"]}, "author": {"contestId": 1581, "members": [{"handle": "StaneLegend"}], "participantType": "CONTESTANT", "ghost": false, "room": 68, "startTimeSeconds": 1632996900}, "programmingLanguage": "GNU C++17", "verdict": "OK", "testset": "TESTS", "passedTestCount": 35, "timeConsumedMillis": 436, "memoryConsumedBytes": 16076800}, {"id": 130367345, "contestId": 1581, "creationTimeSeconds": 1633003387, "relativeTimeSeconds": 6487, "problem": {"contestId": 1581, "index": "E", "name": "Train Maintenance", "type": "PROGRAMMING", "points": 2500.0, "rating": 2200, "tags": ["brute force", "data structures", "implementation"]}, "author": {"contestId": 1581, "members": [{"handle": "StaneLegend"}], "participantType": "CONTESTANT", "ghost": false, "room": 68, "startTimeSeconds": 1632996900}, "programmingLanguage": "GNU C++17", "verdict": "WRONG_ANSWER", "testset": "PRETESTS", "passedTestCount": 4, "timeConsumedMillis": 0, "memoryConsumedBytes": 10752000}, {"id": 130350702, "contestId": 1581, "creationTimeSeconds": 1632999567, "relativeTimeSeconds": 2667, "problem": {"contestId": 1581, "index": "C", "name": "Portal", "type": "PROGRAMMING", "points": 1500.0, "rating": 1700, "tags": ["brute force", "dp", "greedy", "implementation"]}, "author": {"contestId": 1581, "members": [{"handle": "StaneLegend"}], "participantType": "CONTESTANT", "ghost": false, "room": 68, "startTimeSeconds": 1632996900}, "programmingLanguage": "GNU C++17", "verdict": "OK", "testset": "TESTS", "passedTestCount": 64, "timeConsumedMillis": 46, "memoryConsumedBytes": 5529600}, {"id": 130340505, "contestId": 1581, "creationTimeSeconds": 1632997561, "relativeTimeSeconds": 661, "problem": {"contestId": 1581, "index": "A", "name": "CQXYM Count Permutations", "type": "PROGRAMMING", "points": 500.0, "rating": 800, "tags": ["combinatorics", "math", "number theory"]}, "author": {"contestId": 1581, "members": [{"handle": "StaneLegend"}], "participantType": "CONTESTANT", "ghost": false, "room": 68, "startTimeSeconds": 1632996900}, "programmingLanguage": "GNU C++17", "verdict": "OK", "testset": "TESTS", "passedTestCount": 10, "timeConsumedMillis": 15, "memoryConsumedBytes": 3788800}, {"id": 130340447, "contestId": 1581, "creationTimeSeconds": 1632997551, "relativeTimeSeconds": 651, "problem": {"contestId": 1581, "index": "B", "name": "Diameter of Graph", "type": "PROGRAMMING", "points": 1000.0, "rating": 1200, "tags": ["constructive algorithms", "graphs", "greedy", "math"]}, "author": {"contestId": 1581, "members": [{"handle": "StaneLegend"}], "participantType": "CONTESTANT", "ghost": false, "room": 68, "startTimeSeconds": 1632996900}, "programmingLanguage": "GNU C++17", "verdict": "OK", "testset": "TESTS", "passedTestCount": 12, "timeConsumedMillis": 62, "memoryConsumedBytes": 3788800}, {"id": 130340389, "contestId": 1581, "creationTimeSeconds": 1632997539, "relativeTimeSeconds": 639, "problem": {"contestId": 1581, "index": "A", "name": "CQXYM Count Permutations", "type": "PROGRAMMING", "points": 500.0, "rating": 800, "tags": ["combinatorics", "math", "number theory"]}, "author": {"contestId": 1581, "members": [{"handle": "StaneLegend"}], "participantType": "CONTESTANT", "ghost": false, "room": 68, "startTimeSeconds": 1632996900}, "programmingLanguage": "GNU C11", "verdict": "COMPILATION_ERROR", "testset": "PRETESTS", "passedTestCount": 0, "timeConsumedMillis": 0, "memoryConsumedBytes": 0}]}